idp_user/__init__.py
idp_user/agents.py
idp_user/apps.py
idp_user/checks.py
idp_user/producer.py
idp_user/schema_extensions.py
idp_user/settings.py
idp_user/signals.py
idp_user/urls.py
idp_user/auth/__init__.py
idp_user/auth/admin.py
idp_user/auth/drf.py
idp_user/auth/ninja.py
idp_user/management/__init__.py
idp_user/management/commands/__init__.py
idp_user/management/commands/put_app_entities_records_to_kafka.py
idp_user/migrations/0001_initial.py
idp_user/migrations/0001_initial_squashed_0005_alter_userrole_id.py
idp_user/migrations/0002_auto_20220120_1617.py
idp_user/migrations/0003_auto_20220513_1025.py
idp_user/migrations/0004_auto_20220817_1526.py
idp_user/migrations/0005_alter_userrole_id.py
idp_user/migrations/0006_userrole_organization_and_more.py
idp_user/migrations/0007_user_demo.py
idp_user/migrations/__init__.py
idp_user/models/__init__.py
idp_user/models/user.py
idp_user/models/user_role.py
idp_user/services/__init__.py
idp_user/services/async_user.py
idp_user/services/base_user.py
idp_user/services/user.py
idp_user/utils/__init__.py
idp_user/utils/choices.py
idp_user/utils/classes.py
idp_user/utils/exceptions.py
idp_user/utils/functions.py
idp_user/utils/typing.py
django_idp_user-3.0.1.dist-info/METADATA
django_idp_user-3.0.1.dist-info/WHEEL
django_idp_user-3.0.1.dist-info/licenses/LICENSE
django_idp_user-3.0.1.dist-info/RECORD
