Metadata-Version: 2.4
Name: django-idp-user
Version: 3.0.1
Summary: A Django app that handles the communication between the IDP and the products for the authorization of users.
Author: Mahmoud Al-Rawy, Euron Metaliaj, Klajdi Çaushi, Aleksandër Nasto, Andi Çuku, Klement Omeri, Lirim Shala
Author-email: hello@cardoai.com
License: Copyright 2023 CardoAI
License-File: LICENSE
Classifier: Development Status :: 5 - Production/Stable
Classifier: Framework :: Django
Classifier: Framework :: Django :: 3.2
Classifier: Framework :: Django :: 4.0
Classifier: Intended Audience :: Developers
Classifier: License :: OSI Approved :: MIT License
Classifier: Operating System :: OS Independent
Classifier: Programming Language :: Python
Classifier: Programming Language :: Python :: 3.9
Classifier: Programming Language :: Python :: 3.10
Classifier: Programming Language :: Python :: 3.11
Classifier: Topic :: Internet :: WWW/HTTP
Classifier: Topic :: Internet :: WWW/HTTP :: Dynamic Content
Classifier: Topic :: Software Development :: Libraries :: Application Frameworks
Classifier: Topic :: Software Development :: Libraries :: Python Modules
Requires-Python: >=3.9
Requires-Dist: boto3
Requires-Dist: django
Requires-Dist: faust-streaming
Requires-Dist: kafka-python
Requires-Dist: pyjwt==2.6.0
Requires-Dist: requests
Provides-Extra: async
Requires-Dist: aiohttp>=3.8.4; extra == 'async'
Requires-Dist: aiokafka>=0.8.1; extra == 'async'
Requires-Dist: django>=4.2.1; extra == 'async'
Provides-Extra: dev
Requires-Dist: black==23.3.0; extra == 'dev'
Requires-Dist: build==0.10.0; extra == 'dev'
Requires-Dist: coverage==7.2.5; extra == 'dev'
Requires-Dist: faker==18.9.0; extra == 'dev'
Requires-Dist: pre-commit==3.3.2; extra == 'dev'
Requires-Dist: pytest-django==4.5.2; extra == 'dev'
Requires-Dist: pytest-sugar==0.9.7; extra == 'dev'
Requires-Dist: pytest==7.3.1; extra == 'dev'
Requires-Dist: ruff==0.0.269; extra == 'dev'
Provides-Extra: docs
Requires-Dist: mdx-include==1.4.2; extra == 'docs'
Requires-Dist: mkdocs-markdownextradata-plugin==0.2.5; extra == 'docs'
Requires-Dist: mkdocs-material==9.1.14; extra == 'docs'
Requires-Dist: termynal==0.3.0; extra == 'docs'
Provides-Extra: drf
Requires-Dist: djangorestframework; extra == 'drf'
Requires-Dist: drf-spectacular; extra == 'drf'
Provides-Extra: ninja
Requires-Dist: django-ninja; extra == 'ninja'
